{"name":"Grace","scopeName":"source.grace","patterns":[{"include":"#comment"},{"include":"#comma"},{"name":"meta.import.grace","match":"(import)\\s*(\".*\")\\s*(as)\\s+([A-z][A-z\\d']*)","captures":{"1":{"name":"keyword.import.grace"},"2":{"name":"string.path.grace"},"3":{"name":"keyword.as.grace"},"4":{"name":"entity.identifier.grace"}}},{"name":"meta.type.literal.grace","begin":"(?:(?\u003c![A-z\\d'])(type)|(=))\\s*\\{","end":"\\}","patterns":[{"include":"#comment"},{"include":"#signature"},{"include":"#bad_names"},{"name":"entity.function.grace","match":"[A-z][A-z\\d']*|[-|@#!%$?\u0026=:\\.\\*~+\\\u003c/\u003e\\\\\\^]*"}],"beginCaptures":{"1":{"name":"keyword.type.grace"},"2":{"name":"keyword.operator.grace"}}},{"name":"meta.type.grace","begin":"(?\u003c![A-z\\d'])(type)(?![A-z\\d'])(?!\\s*\\{)","end":"(?==)","patterns":[{"include":"#comment"},{"name":"meta.type.generic.grace","begin":"([A-z][A-z\\d']*)(\u003c)","end":"(\u003e)","patterns":[{"include":"#comment"},{"include":"#bad_names"},{"include":"#bad_operators"},{"include":"#comma"},{"name":"entity.type.generic.grace","match":"[A-z][A-z\\d']*"}],"beginCaptures":{"1":{"name":"entity.type.grace"},"2":{"name":"keyword.operator.grace"}},"endCaptures":{"1":{"name":"keyword.type.generic.grace"}}},{"begin":"(?\u003c![A-z\\d'])(is)(?![A-z\\d'])","end":"(?==)","patterns":[{"include":"$self"},{"name":"support.type.annotation.grace","match":"[A-z][A-z\\d']*"}],"beginCaptures":{"1":{"name":"keyword.grace"}}},{"include":"#bad_names"},{"name":"entity.type.grace","match":"[A-z][A-z\\d']*"},{"include":"$self"}],"beginCaptures":{"1":{"name":"keyword.type.grace"}},"endCaptures":{"1":{"name":"keyword.operator.grace"}}},{"name":"meta.method.grace","begin":"(?\u003c![A-z\\d'])(method)(?![A-z\\d'])","end":"(?=\\{)","patterns":[{"include":"#comment"},{"include":"#signature"},{"name":"entity.function.grace","match":"[A-z][A-z\\d']*|[-|@#!%$?\u0026=:\\.\\*~+\\\u003c/\u003e\\\\\\^]*"}],"beginCaptures":{"1":{"name":"keyword.grace"}}},{"name":"meta.class.grace","begin":"\\b(class)(?![A-z\\d'])","end":"(?=\\{)","patterns":[{"include":"#comment"},{"include":"#signature"},{"name":"keyword.operator.class.grace","match":"\\."},{"name":"meta.name.class.grace","match":"(?\u003c=class)\\s*([A-z][A-z\\d']*)\\s*(\\.)","captures":{"1":{"name":"entity.class.grace"},"2":{"name":"keyword.operator.grace"}}},{"name":"entity.class.grace","match":"[A-z][A-z\\d']*|[-|@#!%$?\u0026=:\\.\\*~+\\\u003c/\u003e\\\\\\^]*"}],"beginCaptures":{"1":{"name":"keyword.class.grace"}}},{"name":"meta.definition.grace","begin":"(?\u003c![A-z\\d'])(def)(?![A-z\\d'])","end":"(?\u003c![^\\w\\d'\\s])(?:(=)|(:=))(?![^\\w\\s])|$","patterns":[{"include":"#comment"},{"include":"#signature_args"},{"begin":"(?\u003c![A-z\\d'])(is)(?![A-z\\d'])","end":"(?=(?\u003c![^\\w\\d'\\s])(?:(=)|(:=))(?![^\\w\\d'\\s]))|$","patterns":[{"include":"$self"},{"name":"support.type.annotation.grace","match":"[A-z][A-z\\d']*"}],"beginCaptures":{"1":{"name":"keyword.grace"}}},{"include":"#bad_names"},{"name":"entity.definition.grace","match":"\\b_\\b|[A-z][A-z\\d']*"}],"beginCaptures":{"1":{"name":"keyword.definition.grace"}},"endCaptures":{"1":{"name":"keyword.operator.grace"},"2":{"name":"invalid.illegal.grace"}}},{"name":"meta.variable.grace","begin":"(?\u003c![A-z\\d'])(var)(?![A-z\\d'])","end":"(?\u003c![^\\w\\d'\\s])(?:(:=)|(=))(?![^\\w\\d'\\s])|$","patterns":[{"include":"#comment"},{"begin":"(?\u003c![^\\w\\d'\\s\\(,])(:)(?![^\\w\\d'\\s\\),])","end":"(?=$|,|\\)|(?\u003c=[^-|@#!%$?\u0026=:\\.\\*~+\\\u003c/\u003e\\\\\\^]|^)(:|=|:=|-\u003e)(?=[^-|@#!%$?\u0026=:\\.\\*~+\\\u003c/\u003e\\\\\\^]|$))","patterns":[{"include":"$self"},{"include":"#type"}],"beginCaptures":{"1":{"name":"keyword.operator.grace"}}},{"begin":"(?\u003c![A-z\\d'])(is)(?![A-z\\d'])","end":"(?=(?\u003c![^\\w\\d'\\s])(?:(=)|(:=))(?![^\\w\\d'\\s]))|$","patterns":[{"include":"$self"},{"name":"support.type.annotation.grace","match":"[A-z][A-z\\d']*"}],"beginCaptures":{"1":{"name":"keyword.grace"}}},{"include":"#bad_names"},{"include":"#bad_operators"},{"name":"entity.variable.grace","match":"\\b_\\b|[A-z][A-z\\d']*"}],"beginCaptures":{"1":{"name":"keyword.variable.grace"}},"endCaptures":{"1":{"name":"keyword.operator.grace"},"2":{"name":"invalid.illegal.grace"}}},{"name":"meta.block.grace","begin":"\\{","end":"\\}","patterns":[{"include":"$self"}]},{"name":"meta.parameters.block.grace","begin":"(?\u003c=\\{)(?=[^{}]*[^-|@#!%$?\u0026=:\\.\\*~+\\\u003c/\u003e\\\\}]-\u003e[^-|@#!%$?\u0026=:\\.\\*~+\\\u003c/\u003e\\\\\\^])","end":"(-\u003e)","patterns":[{"include":"#comment"},{"include":"#signature_args"},{"include":"#comma"},{"include":"#number"},{"include":"#string"},{"include":"#bad_names"},{"include":"#bad_operators"},{"name":"entity.parameter.grace","match":"[A-z][A-z\\d']*"}],"endCaptures":{"1":{"name":"keyword.operator.grace"}}},{"include":"#string"},{"include":"#generic"},{"name":"keyword.control.grace","match":"(?\u003c![A-z\\d'])(return)(?![A-z\\d'])"},{"name":"keyword.operator.grace","match":"(?\u003c=[^-|@#!%$?\u0026=:\\.\\*~+\\\u003c/\u003e\\\\\\^]|^)(:|=|:=|\\.|-\u003e)(?=[^-|@#!%$?\u0026=:\\.\\*~+\\\u003c/\u003e\\\\\\^]|$)"},{"name":"support.function.operator.grace","match":"[-|@#!%$?\u0026=:\\.\\*~+\\\u003c/\u003e\\\\\\^]*"},{"name":"keyword.grace","match":"(?\u003c![A-z\\d'])(dialect|import|as|object|method|class|type|def|var|where|is|inherits)(?![A-z\\d'])"},{"include":"#number"},{"name":"variable.language.self.grace","match":"(?\u003c![A-z\\d'])(super|self|outer)(?![A-z\\d'])"},{"name":"constant.language.boolean.true.grace","match":"(?\u003c![A-z\\d'])true(?![A-z\\d'])"},{"name":"constant.language.boolean.false.grace","match":"(?\u003c![A-z\\d'])false(?![A-z\\d'])"},{"name":"support.type.grace","match":"(?\u003c![A-z\\d'])[A-Z][A-z\\d']*(?![A-z\\d']|\\s*\\.\\s*[A-z])"}],"repository":{"bad_names":{"name":"invalid.illegal.grace","match":"(?\u003c![A-z\\d'])(dialect|import|as|object|method|class|type|def|var|where|is|inherits|self|super|outer)(?![A-z\\d'])"},"bad_operators":{"name":"invalid.illegal.grace","match":"[-|@#!%$?\u0026=:\\.\\*~+\\\u003c/\u003e\\\\\\^]+"},"comma":{"name":"keyword.grace","match":","},"comment":{"name":"comment.line.grace","match":"//.*$"},"generic":{"name":"meta.type.generic.grace","begin":"(?:([A-Z][A-z\\d']*)|[a-z][A-z\\d']*)(\u003c)(?![-|@#!%$?\u0026=:\\.\\*~+\\\u003c/\u003e\\\\\\^])","end":"(\u003e)","patterns":[{"include":"#comment"},{"include":"#generic"},{"include":"$self"},{"include":"#type"}],"beginCaptures":{"1":{"name":"support.type.grace"},"2":{"name":"keyword.operator.grace"}},"endCaptures":{"1":{"name":"keyword.operator.grace"}}},"number":{"name":"constant.numeric.grace","match":"\\b((0(x|X)[0-9a-fA-F]+)|([0-9]+(\\.[0-9]+)?))\\b"},"signature":{"name":"meta.signature.grace","patterns":[{"include":"#comment"},{"begin":"(?\u003c=[^-|@#!%$?\u0026=:\\.\\*~+\\\u003c/\u003e\\\\\\^]|^)(-\u003e)(?=[^-|@#!%$?\u0026=:\\.\\*~+\\\u003c/\u003e\\\\\\^]|$)","end":"(?=(?\u003c![A-z\\d'])is(?![A-z\\d'])|\\{|\\}|(?\u003c=[A-z\\d'\"\u003e)])(?\u003c!-\u003e)\\s+$)","patterns":[{"include":"$self"},{"include":"#type"}],"beginCaptures":{"1":{"name":"keyword.operator.grace"}}},{"name":"meta.signature.prefix.grace","match":"(prefix)\\s*(?:(:(?:=?)(?=[^-|@#!%$?\u0026=:\\.\\*~+\\\u003c/\u003e\\\\\\^]))|([-|@#!%$?\u0026=:\\.\\*~+\\\u003c/\u003e\\\\\\^]*))","captures":{"1":{"name":"keyword.grace"},"2":{"name":"invalid.illegal.grace"},"3":{"name":"entity.function.grace"}}},{"name":"meta.signature.assign.grace","match":"([A-z][A-z0-9']*)\\s*(:=)\\s*(?=\\()","captures":{"1":{"name":"entity.function.grace"},"2":{"name":"keyword.operator.grace"}}},{"name":"meta.signature.binary.grace","match":"(?:(:(?:=?))|([-|@#!%$?\u0026=:\\.\\*~+\\\u003c/\u003e\\\\\\^]+))\\s*(?=\\()","captures":{"1":{"name":"invalid.illegal.grace"},"2":{"name":"entity.function.grace"}}},{"begin":"(?\u003c![A-z\\d'])(is)(?![A-z\\d'])","end":"(?=\\{|\\}|(?\u003c=[A-z\\d'\"\u003e)])(?\u003c!is)\\s+$)","patterns":[{"include":"$self"},{"name":"support.annotation.grace","match":"[A-z][A-z\\d']*"}],"beginCaptures":{"1":{"name":"keyword.grace"}}},{"name":"meta.signature.parameters.grace","begin":"\\(","end":"\\)","patterns":[{"include":"#signature_args"}]},{"begin":"(?\u003c=\\w)(\u003c)","end":"(\u003e)","patterns":[{"include":"#comment"},{"include":"#comma"},{"name":"support.type.grace","match":"[A-z][A-z0-9']*"}],"beginCaptures":{"1":{"name":"keyword.generic.grace"}},"endCaptures":{"1":{"name":"keyword.generic.grace"}}},{"include":"#bad_names"},{"include":"#bad_operators"},{"name":"entity.function.grace","match":"[A-z][A-z\\d']*(?=\\s*[,\\:\\)])"}]},"signature_args":{"name":"meta.signature.grace","patterns":[{"include":"#comment"},{"name":"keyword.variadic.grace","match":"\\*"},{"begin":"(?\u003c![^\\w\\d'\\s\\(,])(:)(?![^\\w\\d'\\s\\),])","end":"(?=,|\\)|(?\u003c=[^-|@#!%$?\u0026=:\\.\\*~+\\\u003c/\u003e\\\\\\^]|^)(:|=|:=|-\u003e)(?=[^-|@#!%$?\u0026=:\\.\\*~+\\\u003c/\u003e\\\\\\^]|$))","patterns":[{"include":"$self"},{"include":"#type"}],"beginCaptures":{"1":{"name":"keyword.operator.grace"}}},{"name":"entity.function.grace","match":"[A-z][A-z\\d']*(?=\\s*[,\\:\\)])"},{"include":"#comma"}]},"string":{"name":"string.quoted.double.grace","begin":"\"","end":"(\")|(\\n)","patterns":[{"name":"constant.character.escape.grace","match":"\\\\(x[0-9A-Fa-f]{2}|[0-2][0-7]{0,2}|3[0-6][0-7]|37[0-7]?|[4-7][0-7]?|.)"},{"name":"source.embedded.grace","begin":"\\{","end":"\\}","patterns":[{"include":"$self"}],"beginCaptures":{"0":{"name":"keyword.interpolation.begin.grace"}},"endCaptures":{"0":{"name":"keyword.interpolation.end.grace"}}}],"beginCaptures":{"0":{"name":"punctuation.definition.string.begin.grace"}},"endCaptures":{"1":{"name":"punctuation.definition.string.end.grace"},"2":{"name":"invalid.illegal.grace"}}},"type":{"name":"support.type.grace","match":"[A-z][A-z\\d']*(?![A-z\\d']|\\s*\\.\\s*[A-z])"}}}
